<?xml version="1.0" encoding="utf-8"?>
<Catalog>
    <CWeaponLegacy id="ZeratulCommanderParticularBeam">
        <EditorCategories value="Race:Zeratul"/>
        <Icon value="Assets\Textures\btn-upgrade-protoss-groundweaponslevel0.dds"/>
        <DisplayEffect value="ZeratulCommanderParticularBeam@Damage"/>
        <TargetFilters value="Visible;Missile,Stasis,Dead,Hidden,Invulnerable"/>
        <Range value="6"/>
        <Period value="1"/>
        <Effect value="ZeratulCommanderParticularBeam@LM"/>
    </CWeaponLegacy>
</Catalog>
