<?xml version="1.0" encoding="utf-8"?>
<Catalog>
    <CActorUnit id="RaynorCommanderMarine" parent="GenericUnitBase" unitName="RaynorCommanderMarine">
        <Aliases value="_UnitSmall"/>
        <Macros value="UnloadDropAnim"/>
        <Macros value="PhysicsDeathsSwarmGround"/>
        <Macros value="TerrainSquibAnimations"/>
        <Macros value="PhysicsDeathsVoidGround"/>
        <On Terms="ActorCreation; ValidatePlayer NoMarineShield" Send="AnimPlay Cover Cover PlayForever 0.000000"/>
        <On Terms="Upgrade.ShieldWall.Add" Send="AnimClear Cover"/>
        <On Terms="Upgrade.ShieldWall.Remove" Send="AnimPlay Cover Cover PlayForever 0.000000"/>
        <On Terms="UnitDeath.RaynorCommanderMarine; AnimPlaying Cover" Target="_DeathModel" Send="AnimPlay Cover Cover PlayForever 0.000000"/>
        <On Terms="Abil.attack.ReadyStart" Send="AnimGroupApply Ready"/>
        <On Terms="WeaponStart.*.AttackStart; WeaponTargetElevation GE 20.000000" Send="AnimBracketStart Attack Attack,Superior"/>
        <On Terms="WeaponStart.*.AttackStart; WeaponTargetElevation LE -20.000000" Send="AnimBracketStart Attack Attack,Inferior"/>
        <On Terms="WeaponStart.*.AttackStart" Send="AnimBracketStart Attack Attack"/>
        <On Terms="WeaponStop.*.AttackStop" Send="AnimBracketStop Attack"/>
        <On Terms="Abil.attack.ReadyStop" Send="AnimGroupRemove Ready"/>
        <On Terms="ModelEvent; ModelEventName SquibStart" Send="Create MarineCheerSquib"/>
        <On Terms="ModelEvent; ModelEventName SquibStop" Target="MarineCheerSquib" Send="Destroy"/>
        <On Terms="ModelEvent; ModelEventName SquibStop" Target="MarineCheerSquibSound" Send="Destroy"/>
        <On Terms="AnimDone; AnimName Cheer" Target="MarineCheerSquib" Send="Destroy"/>
        <On Terms="AnimDone; AnimName Cheer" Target="MarineCheerSquibSound" Send="Destroy"/>
        <On Terms="UnitHeightUpdate.*.Land" Send="Create Marine_Land"/>
        <On Terms="UnitDeathCustomize; PassChance 100.000000; ValidateUnit IsNotNeuralParasited" Send="Create Marine_Death"/>
        <On Terms="UnitDeathCustomize; PassChance 100.000000; !ValidateUnit IsNotNeuralParasited" Send="Create Marine_Death_NP"/>
        <Model value="RaynorCommanderMarine@Marine"/>
        <ModelFlags index="OutlineEmitter" value="1"/>
        <BuildModel value="RaynorCommanderMarine@Marine"/>
        <DeathArray index="Normal" ModelLink="RaynorCommanderMarine@MarineDeath" SoundLink="RaynorCommanderMarine@DeathFXBloodSpray"/>
        <DeathArray index="Blast" ModelLink="RaynorCommanderMarine@MarineDeathBlast"/>
        <DeathArray index="Disintegrate" ModelLink="RaynorCommanderMarine@MarineDeathAcid" SoundLink="Uni_DeathFXAcid"/>
        <DeathArray index="Eat" AnimProps="Stand" ModelLink="RaynorCommanderMarine@MarineDeathEat" SoundLink="RaynorCommanderMarine@DeathFXEat"/>
        <DeathArray index="Eviscerate" ModelLink="RaynorCommanderMarine@MarineDeathEviscerate" SoundLink="RaynorCommanderMarine@DeathFXEviscerate"/>
        <DeathArray index="Fire" ModelLink="RaynorCommanderMarine@MarineDeathFire" SoundLink="RaynorCommanderMarine@DeathFXFire"/>
        <DeathArray index="Silentkill" SoundLink="Uni_DeathFXSilentKill"/>
        <DeathArray index="Squish" SoundLink="RaynorCommanderMarine@DeathFXBloodSpray"/>
        <DeathCustoms ModelLink="TerranSmallBiologicalUnitDeathLow" Name="AntiGravTerran"/>
        <DeathCustoms ModelLink="RaynorCommanderMarine@MarineDeathRagdoll" Name="RagdollBasic">
            <BodySquibs Name="None"/>
        </DeathCustoms>
        <DeathCustoms Name="RagdollSiegeTank" InheritsFrom="RagdollBasic"/>
        <DeathCustoms Name="RagdollNuke" InheritsFrom="RagdollBasic">
            <BodySquibs Name="Fire"/>
        </DeathCustoms>
        <DeathCustoms Name="RagdollFire" InheritsFrom="RagdollBasic">
            <BodySquibs Name="Fire"/>
        </DeathCustoms>
        <DeathCustoms Name="RagdollAcid" InheritsFrom="RagdollBasic">
            <BodySquibs Name="Acid"/>
        </DeathCustoms>
        <DeathCustoms Name="RagdollBaneling" InheritsFrom="RagdollBasic">
            <BodySquibs Name="Acid"/>
        </DeathCustoms>
        <DeathCustoms Name="RagdollUltraUnburrow" InheritsFrom="RagdollBasic"/>
        <DeathCustoms ActorModel="SpineCrawlerHurlDeathRagdollBloodPrevent" ModelLink="RaynorCommanderMarine@MarineDeathRagdoll" Name="RagdollSpineCrawlerHurl">
            <BodySquibs Name="None"/>
        </DeathCustoms>
        <DeathCustoms Name="RagdollOverkillDPRH" InheritsFrom="RagdollBasic"/>
        <DeathCustoms Name="RagdollOverkillDOI" InheritsFrom="RagdollBasic"/>
        <DeathCustoms Name="RagdollMidair" InheritsFrom="RagdollBasic"/>
        <DeathActorModel value="UnitDeathModelWithDeathMotionGround"/>
        <PlacementModel value="RaynorCommanderMarine@Marine"/>
        <PortraitModel value="RaynorCommanderMarine@MarinePortrait"/>
        <StandAnimTurnTime value="4"/>
        <TerrainSquibs>
            <MovementDistance value="0.150000,0.150000"/>
            <IdlePeriod value="0.100000,0.250000"/>
            <RangeUp value="0.600000"/>
            <RangeDown value="0.600000"/>
            <AttachQuery Methods="AMFilterCenter"/>
            <Visuals TerrainPhysicsMaterial="Water" ActorModel="TerrainSquibHarnessContinuous" ModelLink="WaterRippleSmall"/>
        </TerrainSquibs>
        <WalkAnimMoveSpeed value="2.25"/>
        <AbilSoundArray AbilCmd="RaynorCommanderStimpack,255" Sound="RaynorCommanderMarine@StimPackVO"/>
        <BarOffset value="40"/>
        <BarWidth value="36"/>
        <GlossaryAnim value="Spell"/>
        <GroupIcon>
            <Image value="Assets\Textures\Wireframe-Terran-Marine.dds"/>
        </GroupIcon>
        <HeroIcon value="Assets\Textures\btn-unit-terran-marine.dds"/>
        <LifeArmorIcon value="Assets\Textures\btn-upgrade-terran-infantryarmorlevel0.dds"/>
        <SoundArray index="Ready" value="RaynorCommanderMarine@Ready"/>
        <SoundArray index="Help" value="RaynorCommanderMarine@Help"/>
        <SoundArray index="What" value="RaynorCommanderMarine@What"/>
        <SoundArray index="Yes" value="RaynorCommanderMarine@Yes"/>
        <SoundArray index="Attack" value="RaynorCommanderMarine@Attack"/>
        <SoundArray index="Pissed" value="RaynorCommanderMarine@Pissed"/>
        <UnitIcon value="Assets\Textures\btn-unit-terran-marine.dds"/>
        <Wireframe>
            <Image value="Assets\Textures\Wireframe-Terran-Marine.dds"/>
        </Wireframe>
    </CActorUnit>
</Catalog>
